pyairios/__init__.py
pyairios/client.py
pyairios/constants.py
pyairios/data_model.py
pyairios/device.py
pyairios/exceptions.py
pyairios/node.py
pyairios/properties.py
pyairios/py.typed
pyairios/registers.py
pyairios/models/__init__.py
pyairios/models/brdg_02r13.py
pyairios/models/factory.py
pyairios/models/vmd_02rps78.py
pyairios/models/vmd_07rps13.py
pyairios/models/vmn_05lm02.py
pyairios-1.1.0.dist-info/METADATA
pyairios-1.1.0.dist-info/WHEEL
pyairios-1.1.0.dist-info/licenses/LICENSE
pyairios-1.1.0.dist-info/RECORD
