Metadata-Version: 2.4
Name: pyairios
Version: 1.1.0
Summary: Python library to interface with Airios RF bridges
Project-URL: Homepage, https://github.com/scabrero/pyairios
Project-URL: Repository, https://github.com/scabrero/pyairios.git
Project-URL: Issues, https://github.com/scabrero/pyairios/issues
Author-email: Samuel Cabrero <samuel@orica.es>
License:                                  Apache License
License-File: LICENSE
Keywords: Airios,RAMSES II,Siber,heat-recovery,modbus,modbus-rtu,modbus-tcp,ventilation
Classifier: Development Status :: 5 - Production/Stable
Classifier: License :: OSI Approved :: Apache Software License
Classifier: Operating System :: OS Independent
Classifier: Programming Language :: Python :: 3.12
Classifier: Topic :: Home Automation
Classifier: Topic :: Scientific/Engineering :: Interface Engine/Protocol Translator
Classifier: Topic :: Software Development :: Libraries :: Python Modules
Requires-Python: >=3.13
Requires-Dist: aiocmd>=0.1.5
Requires-Dist: pymodbus<4,>=3.11.2
Requires-Dist: pyserial-asyncio>=0.6
